CHANGES
LICENSE
MANIFEST.in
README.rst
__main__.py
setup.cfg
setup.py
pss.egg-info/PKG-INFO
pss.egg-info/SOURCES.txt
pss.egg-info/dependency_links.txt
pss.egg-info/entry_points.txt
pss.egg-info/top_level.txt
psslib/__init__.py
psslib/contentmatcher.py
psslib/defaultpssoutputformatter.py
psslib/driver.py
psslib/filefinder.py
psslib/matchresult.py
psslib/outputformatter.py
psslib/pss.py
psslib/utils.py
psslib/colorama/__init__.py
psslib/colorama/ansi.py
psslib/colorama/ansitowin32.py
psslib/colorama/initialise.py
psslib/colorama/win32.py
psslib/colorama/winterm.py
scripts/pss
scripts/pss.py