Metadata-Version: 2.1
Name: pss
Version: 1.45
Summary: Tool for grepping through source code
Home-page: https://github.com/eliben/pss
Author: Eli Bendersky
Author-email: eliben@gmail.com
Maintainer: Eli Bendersky
License: Public domain
Platform: Cross Platform
Classifier: Programming Language :: Python :: 2
Classifier: Programming Language :: Python :: 3
License-File: LICENSE
